Infloat/__init__.py
Infloat/client.py
Infloat/core/__init__.py
Infloat/core/api_error.py
Infloat/core/client_wrapper.py
Infloat/core/datetime_utils.py
Infloat/core/file.py
Infloat/core/http_client.py
Infloat/core/jsonable_encoder.py
Infloat/core/pydantic_utilities.py
Infloat/core/query_encoder.py
Infloat/core/remove_none_from_dict.py
Infloat/core/request_options.py
Infloat/core/serialization.py
Infloat/errors/__init__.py
Infloat/errors/unprocessable_entity_error.py
Infloat/py.typed
Infloat/types/__init__.py
Infloat/types/client_config.py
Infloat/types/client_response.py
Infloat/types/http_validation_error.py
Infloat/types/model_response.py
Infloat/types/project_response.py
Infloat/types/token.py
Infloat/types/training_result_response.py
Infloat/types/training_status.py
Infloat/types/user_response.py
Infloat/types/validation_error.py
Infloat/types/validation_error_loc_item.py
Infloat/version.py
infloat_py-0.2.2.dist-info/METADATA
infloat_py-0.2.2.dist-info/WHEEL
infloat_py-0.2.2.dist-info/RECORD
